MANIFEST.in
README.rst
setup.py
syncify/__init__.py
syncify/syncify.py
syncify.egg-info/PKG-INFO
syncify.egg-info/SOURCES.txt
syncify.egg-info/dependency_links.txt
syncify.egg-info/not-zip-safe
syncify.egg-info/top_level.txt