Metadata-Version: 1.1
Name: syncify
Version: 0.1
Summary: Wrap your asynchronous functions so they behave like synchronous function.
Home-page: https://github.com/ccorcos/syncify
Author: Chet Corcos
Author-email: ccorcos@gmail
License: MIT
Keywords: async sync synchronous asynchronous
Platform: UNKNOWN
Classifier: Development Status :: 2 - Pre-Alpha
Classifier: Programming Language :: Python :: 2.7
